setup.py
CambiosNoDeseados.egg-info/PKG-INFO
CambiosNoDeseados.egg-info/SOURCES.txt
CambiosNoDeseados.egg-info/dependency_links.txt
CambiosNoDeseados.egg-info/entry_points.txt
CambiosNoDeseados.egg-info/requires.txt
CambiosNoDeseados.egg-info/top_level.txt
script/Cliente
script/Servidor
src/Cambios/__init__.py
src/Cambios/cartas.py
src/Cambios/cliente.py
src/Cambios/generador.py
src/Cambios/ia.py
src/Cambios/interfaz.py
src/Cambios/juego.py
src/Cambios/main.py
src/Cambios/reglas.py
src/Cambios/servidor.py
src/Cambios/Arte/AgilidadAvansada.png
src/Cambios/Arte/AgilidadBasica.png
src/Cambios/Arte/AlmaAmarilla.png
src/Cambios/Arte/AlmaAzul.png
src/Cambios/Arte/AlmaBlanca.png
src/Cambios/Arte/AlmaRoja.png
src/Cambios/Arte/Cazador.png
src/Cambios/Arte/Cortadora.png
src/Cambios/Arte/Defensora.png
src/Cambios/Arte/DiabloDanzante.png
src/Cambios/Arte/EnergiaAvansada.png
src/Cambios/Arte/EnergiaBasica.png
src/Cambios/Arte/Fondo.png
src/Cambios/Arte/GusanoProfundo.png
src/Cambios/Arte/PezPlata.png
src/Cambios/Arte/ResistenciaAvansada.png
src/Cambios/Arte/ResistenciaBasica.png
src/Cambios/Arte/SerpienteVestijial.png
src/Cambios/Arte/Vacio.png
src/Cambios/Arte/VenusAtrapaHombres.png
src/Cambios/Cartas/AgilidadAvansada.xml
src/Cambios/Cartas/AgilidadBasica.xml
src/Cambios/Cartas/AlmaAmarilla.xml
src/Cambios/Cartas/AlmaAzul.xml
src/Cambios/Cartas/AlmaBlanca.xml
src/Cambios/Cartas/AlmaRoja.xml
src/Cambios/Cartas/EnergiaAvanzada.xml
src/Cambios/Cartas/EnergiaBasica.xml
src/Cambios/Cartas/Entropia_1.xml
src/Cambios/Cartas/Entropia_2.xml
src/Cambios/Cartas/Entropia_3.xml
src/Cambios/Cartas/Induccion_1.xml
src/Cambios/Cartas/Induccion_2.xml
src/Cambios/Cartas/Induccion_3.xml
src/Cambios/Cartas/Radiacion_1.xml
src/Cambios/Cartas/Radiacion_2.xml
src/Cambios/Cartas/ResistenciaAvansada.xml
src/Cambios/Cartas/ResistenciaBasica.xml
src/Cambios/Estilos/alt.css
src/Cambios/Estilos/alt.xsl
src/Cambios/Estilos/alt.xsl~
src/Cambios/Estilos/esquema.dtd
src/Cambios/Estilos/esquema.dtd~
src/Cambios/Estilos/estandar.css
src/Cambios/Estilos/estandar.xsl
src/Cambios/Estilos/historia.css
src/Cambios/Estilos/historia_superior.css
src/Cambios/Habilidades/Dañar.py
src/Cambios/Habilidades/Empujar.py
src/Cambios/Habilidades/__init__.py
