Metadata-Version: 1.1
Name: CambiosNoDeseados
Version: 0.0.2
Summary: Cambios No Deseados - Conbinación de un RPG Tactico y un TCG
Home-page: https://bitbucket.org/WolfangT/cambiosnodeseadoscd
Author: Wolfang Torres
Author-email: Wolfang.Torres@gmail.com
License: MIT
Platform: UNKNOWN
Classifier: Development Status :: 2 - Pre-Alpha
Classifier: Intended Audience :: Gamers
Classifier: Topic :: Games/EntertainmentTopic :: Games/Entertainment :: Turn Based StrategyTopic :: Games/Entertainment :: SimulationLicense :: OSI Approved :: MIT License
Classifier: Natural Language :: SpanishProgramming Language :: Python :: 2 :: Only
Classifier: Programming Language :: Python :: 2.7
